python_storyboardclient-0.2.0.dist-info/METADATA
python_storyboardclient-0.2.0.dist-info/RECORD
python_storyboardclient-0.2.0.dist-info/WHEEL
python_storyboardclient-0.2.0.dist-info/pbr.json
python_storyboardclient-0.2.0.dist-info/top_level.txt
storyboardclient/__init__.py
storyboardclient/_i18n.py
storyboardclient/base.py
storyboardclient/_apiclient/__init__.py
storyboardclient/_apiclient/auth.py
storyboardclient/_apiclient/base.py
storyboardclient/_apiclient/client.py
storyboardclient/_apiclient/exceptions.py
storyboardclient/_apiclient/fake_client.py
storyboardclient/_apiclient/utils.py
storyboardclient/auth/__init__.py
storyboardclient/auth/oauth.py
storyboardclient/tests/__init__.py
storyboardclient/tests/base.py
storyboardclient/tests/test_base/__init__.py
storyboardclient/tests/test_base/test_base_HTTPClient.py
storyboardclient/tests/test_base/test_base_manager.py
storyboardclient/tests/test_base/test_base_nested_manager.py
storyboardclient/tests/test_base/test_base_object.py
storyboardclient/tests/v1/__init__.py
storyboardclient/tests/v1/subscription_events.py
storyboardclient/tests/v1/test_branches.py
storyboardclient/tests/v1/test_milestones.py
storyboardclient/tests/v1/test_project_groups.py
storyboardclient/tests/v1/test_projects.py
storyboardclient/tests/v1/test_stories.py
storyboardclient/tests/v1/test_subscriptions.py
storyboardclient/tests/v1/test_tags.py
storyboardclient/tests/v1/test_tasks.py
storyboardclient/tests/v1/test_teams.py
storyboardclient/tests/v1/test_user_preferences.py
storyboardclient/tests/v1/test_users.py
storyboardclient/v1/__init__.py
storyboardclient/v1/boards.py
storyboardclient/v1/branches.py
storyboardclient/v1/client.py
storyboardclient/v1/due_dates.py
storyboardclient/v1/milestones.py
storyboardclient/v1/project_groups.py
storyboardclient/v1/projects.py
storyboardclient/v1/stories.py
storyboardclient/v1/subscription_events.py
storyboardclient/v1/subscriptions.py
storyboardclient/v1/system_info.py
storyboardclient/v1/tags.py
storyboardclient/v1/tasks.py
storyboardclient/v1/teams.py
storyboardclient/v1/timeline.py
storyboardclient/v1/user_preferences.py
storyboardclient/v1/user_tokens.py
storyboardclient/v1/users.py
